<?xml version="1.0" encoding="UTF-8"?>
<h:html xmlns="http://www.w3.org/2002/xforms" xmlns:ev="http://www.w3.org/2001/xml-events" xmlns:h="http://www.w3.org/1999/xhtml" xmlns:jr="http://openrosa.org/javarosa" xmlns:xsd="http://www.w3.org/2001/XMLSchema">
  <h:head>
    <h:title>Sample Form 1</h:title>
    <model>
      <instance>
        <data id="1" version="1">
          <q1/>
          <q2/>
          <q3/>
          <q4/>
          <q5/>
          <q6/>
          <q7_1/>
          <q7_2/>
          <q8/>
          <q9/>
          <q10/>
          <q11/>
        </data>
      </instance>
      <itext>
        <translation lang="English">
          <text id="q1:label">
            <value>Text Question Title 1</value>
          </text>
          <text id="q1:hint">
            <value>Question Hint 1</value>
          </text>
          <text id="q2:label">
            <value>Long Text Question Title 2</value>
          </text>
          <text id="q2:hint">
            <value>Question Hint 2</value>
          </text>
          <text id="q3:label">
            <value>Integer Question Title 3</value>
          </text>
          <text id="q3:hint">
            <value>Question Hint 3</value>
          </text>
          <text id="q4:label">
            <value>Decimal Question Title 4</value>
          </text>
          <text id="q4:hint">
            <value>Question Hint 4</value>
          </text>
          <text id="q5:label">
            <value>Location Question Title 5</value>
          </text>
          <text id="q5:hint">
            <value>Question Hint 5</value>
          </text>
          <text id="q6:label">
            <value>Select One Question Title 6</value>
          </text>
          <text id="q6:hint">
            <value>Question Hint 6</value>
          </text>
          <text id="q7_1:label">
            <value>Multilevel Select One Question Title 7 - Kingdom</value>
          </text>
          <text id="q7_1:hint">
            <value>Question Hint 7</value>
          </text>
          <text id="q7_2:label">
            <value>Multilevel Select One Question Title 7 - Species</value>
          </text>
          <text id="q7_2:hint">
            <value>Question Hint 7</value>
          </text>
          <text id="q8:label">
            <value>Select Multiple Question Title 8</value>
          </text>
          <text id="q8:hint">
            <value>Question Hint 8</value>
          </text>
          <text id="q9:label">
            <value>Datetime Question Title 9</value>
          </text>
          <text id="q9:hint">
            <value>Question Hint 9</value>
          </text>
          <text id="q10:label">
            <value>Date Question Title 10</value>
          </text>
          <text id="q10:hint">
            <value>Question Hint 10</value>
          </text>
          <text id="q11:label">
            <value>Time Question Title 11</value>
          </text>
          <text id="q11:hint">
            <value>Question Hint 11</value>
          </text>
          <text id="on2">
            <value>Cat</value>
          </text>
          <text id="on3">
            <value>Dog</value>
          </text>
          <text id="on5">
            <value>Animal</value>
          </text>
          <text id="on8">
            <value>Plant</value>
          </text>
          <text id="on12">
            <value>Cat</value>
          </text>
          <text id="on13">
            <value>Dog</value>
          </text>
        </translation>
      </itext>
      <bind nodeset="/data/q1" type="string"/>
      <bind nodeset="/data/q2" type="string"/>
      <bind nodeset="/data/q3" type="int"/>
      <bind nodeset="/data/q4" type="decimal"/>
      <bind nodeset="/data/q5" type="geopoint"/>
      <bind nodeset="/data/q6" type="select1"/>
      <bind nodeset="/data/q7_1" type="select1"/>
      <bind nodeset="/data/q7_2" type="string"/>
      <bind nodeset="/data/q8" type="select"/>
      <bind nodeset="/data/q9" type="dateTime"/>
      <bind nodeset="/data/q10" type="date"/>
      <bind nodeset="/data/q11" type="time"/>
    </model>
  </h:head>
  <h:body>
    <input ref="/data/q1">
      <label ref="jr:itext('q1:label')"/>
      <hint ref="jr:itext('q1:hint')"/>
    </input>
    <input ref="/data/q2" rows="5">
      <label ref="jr:itext('q2:label')"/>
      <hint ref="jr:itext('q2:hint')"/>
    </input>
    <input ref="/data/q3">
      <label ref="jr:itext('q3:label')"/>
      <hint ref="jr:itext('q3:hint')"/>
    </input>
    <input ref="/data/q4">
      <label ref="jr:itext('q4:label')"/>
      <hint ref="jr:itext('q4:hint')"/>
    </input>
    <input ref="/data/q5">
      <label ref="jr:itext('q5:label')"/>
      <hint ref="jr:itext('q5:hint')"/>
    </input>
    <select1 ref="/data/q6">
      <label ref="jr:itext('q6:label')"/>
      <hint ref="jr:itext('q6:hint')"/>
      <item>
        <label ref="jr:itext('on2')"/>
        <value>on2</value>
      </item>
      <item>
        <label ref="jr:itext('on3')"/>
        <value>on3</value>
      </item>
    </select1>
    <select1 ref="/data/q7_1">
      <label ref="jr:itext('q7_1:label')"/>
      <hint ref="jr:itext('q7_1:hint')"/>
      <item>
        <label ref="jr:itext('on5')"/>
        <value>on5</value>
      </item>
      <item>
        <label ref="jr:itext('on8')"/>
        <value>on8</value>
      </item>
    </select1>
    <input ref="/data/q7_2" query="instance('os2')/root/item[parent_id=/data/q7_1]">
      <label ref="jr:itext('q7_2:label')"/>
      <hint ref="jr:itext('q7_2:hint')"/>
    </input>
    <select ref="/data/q8">
      <label ref="jr:itext('q8:label')"/>
      <hint ref="jr:itext('q8:hint')"/>
      <item>
        <label ref="jr:itext('on12')"/>
        <value>on12</value>
      </item>
      <item>
        <label ref="jr:itext('on13')"/>
        <value>on13</value>
      </item>
    </select>
    <input ref="/data/q9">
      <label ref="jr:itext('q9:label')"/>
      <hint ref="jr:itext('q9:hint')"/>
    </input>
    <input ref="/data/q10">
      <label ref="jr:itext('q10:label')"/>
      <hint ref="jr:itext('q10:hint')"/>
    </input>
    <input ref="/data/q11">
      <label ref="jr:itext('q11:label')"/>
      <hint ref="jr:itext('q11:hint')"/>
    </input>
  </h:body>
</h:html>
